{
  "parent": "minecraft:recipes/root",
  "rewards": {
    "recipes": [
      "tesla_coil:repair_exposed_tesla_secondary_coil"
    ]
  },
  "criteria": {
    "has_secondary_coil": {
      "trigger": "minecraft:inventory_changed",
      "conditions": {
        "items": [
          {
            "items": [
              "tesla_coil:tesla_secondary_coil"
            ]
          }
        ]
      }
    },
    "has_weathered_secondary_coil": {
      "trigger": "minecraft:inventory_changed",
      "conditions": {
        "items": [
          {
            "items": [
              "tesla_coil:exposed_tesla_secondary_coil"
            ]
          }
        ]
      }
    },
    "has_the_recipe": {
      "trigger": "minecraft:recipe_unlocked",
      "conditions": {
        "recipe": "tesla_coil:repair_exposed_tesla_secondary_coil"
      }
    }
  },
  "requirements": [
    [
      "has_secondary_coil",
      "has_weathered_secondary_coil",
      "has_the_recipe"
    ]
  ]
}